ed/__init__.py
ed/buffer.py
ed-0.1.0.dist-info/LICENSE
ed-0.1.0.dist-info/METADATA
ed-0.1.0.dist-info/WHEEL
ed-0.1.0.dist-info/top_level.txt
ed-0.1.0.dist-info/RECORD
